TrustDecoderss.py
trustdecoderss-2.1.dist-info/LICENSE
trustdecoderss-2.1.dist-info/METADATA
trustdecoderss-2.1.dist-info/WHEEL
trustdecoderss-2.1.dist-info/RECORD
