Metadata-Version: 2.1
Name: TrustDecoderss
Version: 2.1
Summary: Simple Tools for decode Trust wallet data, from extensions wallet, TrustWallet.
License: MIT
Keywords: extensions,TrustWallet,walletdecode,Trust,evm,crypto,decrypt,wallet
Author: JeanClaude89
Requires-Python: >=3.7,<4.0
Classifier: License :: OSI Approved :: MIT License
Classifier: Programming Language :: Python :: 3
Classifier: Programming Language :: Python :: 3.7
Classifier: Programming Language :: Python :: 3.8
Classifier: Programming Language :: Python :: 3.9
Classifier: Programming Language :: Python :: 3.10
Classifier: Programming Language :: Python :: 3.11
Classifier: Programming Language :: Python :: 3.12
Requires-Dist: Cipherbcryptors (>=1.3)
Requires-Dist: ccl_leveldbases (>=1.2)
Requires-Dist: pycryptodome (>=3.20.0)
